py_mcp_installer/__init__.py
py_mcp_installer/cli.py
py_mcp_installer/command_builder.py
py_mcp_installer/config_manager.py
py_mcp_installer/exceptions.py
py_mcp_installer/installation_strategy.py
py_mcp_installer/installer.py
py_mcp_installer/mcp_doctor.py
py_mcp_installer/mcp_inspector.py
py_mcp_installer/platform_detector.py
py_mcp_installer/types.py
py_mcp_installer/utils.py
py_mcp_installer/platforms/__init__.py
py_mcp_installer/platforms/claude_code.py
py_mcp_installer/platforms/codex.py
py_mcp_installer/platforms/cursor.py
py_mcp_installer-0.1.5.dist-info/licenses/LICENSE
py_mcp_installer-0.1.5.dist-info/METADATA
py_mcp_installer-0.1.5.dist-info/WHEEL
py_mcp_installer-0.1.5.dist-info/entry_points.txt
py_mcp_installer-0.1.5.dist-info/top_level.txt
py_mcp_installer-0.1.5.dist-info/RECORD
