Metadata-Version: 2.4
Name: py-mcp-installer
Version: 0.1.5
Summary: Universal MCP server installer for AI coding tools
Author-email: Bob Matlack <bob@matlack.nyc>
License: MIT
Project-URL: Homepage, https://github.com/bobmatnyc/py-mcp-installer-service
Project-URL: Documentation, https://github.com/bobmatnyc/py-mcp-installer-service/tree/main/docs
Project-URL: Repository, https://github.com/bobmatnyc/py-mcp-installer-service
Project-URL: Issues, https://github.com/bobmatnyc/py-mcp-installer-service/issues
Keywords: mcp,model-context-protocol,installer,claude-code,cursor,ai-tools
Classifier: Development Status :: 3 - Alpha
Classifier: Intended Audience :: Developers
Classifier: License :: OSI Approved :: MIT License
Classifier: Programming Language :: Python :: 3
Classifier: Programming Language :: Python :: 3.10
Classifier: Programming Language :: Python :: 3.11
Classifier: Programming Language :: Python :: 3.12
Classifier: Topic :: Software Development :: Libraries :: Python Modules
Requires-Python: >=3.10
License-File: LICENSE
Requires-Dist: pydantic>=2.0.0
Requires-Dist: typing-extensions>=4.0.0
Requires-Dist: tomli-w>=1.0.0
Requires-Dist: tomli>=2.0.0; python_version < "3.11"
Provides-Extra: dev
Requires-Dist: pytest>=7.0.0; extra == "dev"
Requires-Dist: pytest-cov>=4.0.0; extra == "dev"
Requires-Dist: black>=23.0.0; extra == "dev"
Requires-Dist: ruff>=0.1.0; extra == "dev"
Requires-Dist: mypy>=1.0.0; extra == "dev"
Dynamic: license-file
